wagtail_newsletter/__init__.py
wagtail_newsletter/actions.py
wagtail_newsletter/apps.py
wagtail_newsletter/audiences.py
wagtail_newsletter/forms.py
wagtail_newsletter/models.py
wagtail_newsletter/panels.py
wagtail_newsletter/rich_text.py
wagtail_newsletter/views.py
wagtail_newsletter/viewsets.py
wagtail_newsletter/wagtail_hooks.py
wagtail_newsletter/campaign_backends/__init__.py
wagtail_newsletter/campaign_backends/mailchimp.py
wagtail_newsletter/migrations/0001_initial.py
wagtail_newsletter/migrations/__init__.py
wagtail_newsletter/static/wagtail_newsletter/css/wagtail_newsletter.css
wagtail_newsletter/static/wagtail_newsletter/js/wagtail_newsletter.js
wagtail_newsletter/templates/wagtail_newsletter/panels/newsletter_panel.html
wagtail_newsletter/templatetags/wagtail_newsletter.py
wagtail_newsletter-0.2.3.dist-info/licenses/LICENSE
wagtail_newsletter-0.2.3.dist-info/WHEEL
wagtail_newsletter-0.2.3.dist-info/METADATA
wagtail_newsletter-0.2.3.dist-info/RECORD
