Metadata-Version: 2.4
Name: wagtail-newsletter
Version: 0.2.3
Summary: Turn Wagtail pages into newsletters.
Author-email: Alex Morega <alex.morega@torchbox.com>
Requires-Python: >=3.10
Classifier: Development Status :: 3 - Alpha
Classifier: Intended Audience :: Developers
Classifier: License :: OSI Approved :: MIT License
Classifier: Operating System :: OS Independent
Classifier: Programming Language :: Python
Classifier: Programming Language :: Python :: 3
Classifier: Programming Language :: Python :: 3.10
Classifier: Programming Language :: Python :: 3.11
Classifier: Programming Language :: Python :: 3.12
Classifier: Programming Language :: Python :: 3.13
Classifier: Framework :: Django
Classifier: Framework :: Django :: 4.2
Classifier: Framework :: Django :: 5.1
Classifier: Framework :: Django :: 5.2
Classifier: Framework :: Wagtail
Classifier: Framework :: Wagtail :: 6
Classifier: Framework :: Wagtail :: 7
License-File: LICENSE
Requires-Dist: Django>=4.2
Requires-Dist: Wagtail>=6.3
Requires-Dist: queryish>=0.2
Requires-Dist: wagtail-newsletter[testing, docs, mailchimp, mrml] ; extra == "dev"
Requires-Dist: psycopg ; extra == "dev"
Requires-Dist: flit ; extra == "dev"
Requires-Dist: sphinx ; extra == "docs"
Requires-Dist: sphinx-wagtail-theme ; extra == "docs"
Requires-Dist: sphinx-autobuild ; extra == "docs"
Requires-Dist: mailchimp-marketing>=3.0.80 ; extra == "mailchimp"
Requires-Dist: mrml>=0.2 ; extra == "mrml"
Requires-Dist: dj-database-url ; extra == "testing"
Requires-Dist: django-debug-toolbar ; extra == "testing"
Requires-Dist: django-stubs ; extra == "testing"
Requires-Dist: pyright ; extra == "testing"
Requires-Dist: pytest ; extra == "testing"
Requires-Dist: pytest-cov ; extra == "testing"
Requires-Dist: pytest-django ; extra == "testing"
Project-URL: Home, https://github.com/wagtail/wagtail-newsletter
Provides-Extra: dev
Provides-Extra: docs
Provides-Extra: mailchimp
Provides-Extra: mrml
Provides-Extra: testing
